proto/__init__.py
proto/__main__.py
proto/argslib.py
proto/builtins.py
proto/expressions.py
proto/lexer.py
proto/parser.py
proto/runtime.py
proto/statements.py
protolang-0.1.0.dist-info/METADATA
protolang-0.1.0.dist-info/WHEEL
protolang-0.1.0.dist-info/entry_points.txt
protolang-0.1.0.dist-info/top_level.txt
protolang-0.1.0.dist-info/RECORD
