Metadata-Version: 2.1
Name: protolang
Version: 0.1.0
Summary: An experimental programming language.
Home-page: https://github.com/dmulholl/proto
Author: Darren Mulholland
License: Public Domain
Platform: UNKNOWN
Classifier: Programming Language :: Python :: 3
Classifier: Operating System :: OS Independent
Classifier: License :: Public Domain
Requires-Python: >=3.8
